decomposition_umap/__init__.py
decomposition_umap/__main__.py
decomposition_umap/decomposition_umap.py
decomposition_umap/embedding.py
decomposition_umap/example.py
decomposition_umap/multiscale_decomposition.py
decomposition_umap/utils.py
decomposition_umap-0.1.0.dist-info/licenses/LICENSE
decomposition_umap-0.1.0.dist-info/METADATA
decomposition_umap-0.1.0.dist-info/WHEEL
decomposition_umap-0.1.0.dist-info/entry_points.txt
decomposition_umap-0.1.0.dist-info/top_level.txt
decomposition_umap-0.1.0.dist-info/RECORD
