Metadata-Version: 2.4
Name: decomposition-umap
Version: 0.1.0
Summary: A Python module for pattern classification and anomaly detection using UMAP dimensionality reduction embedding on decomposed data using Constrained Diffusion
Author-email: Guang-Xing Li <ligx.ngc7293@gmail.com>
License: GPLv3
Requires-Python: >=3.0
License-File: LICENSE
Requires-Dist: numpy>=1.00
Requires-Dist: umap-learn>=0.4.0
Requires-Dist: constrained-diffusion>=1.0.0
Requires-Dist: scikit-learn>=1.0.0
Dynamic: license-file
